Metadata-Version: 2.4
Name: llama-index-readers-wordlift
Version: 0.4.1
Summary: llama-index readers wordlift integration
Author-email: Your Name <you@example.com>
Maintainer: msftwarelab
License-Expression: MIT
License-File: LICENSE
Keywords: graphql,knowledge graph,seo,structured data,wordlift
Requires-Python: <4.0,>=3.9
Requires-Dist: bs4
Requires-Dist: graphql-core<4,>=3.2.3
Requires-Dist: langchain<0.2,>=0.1.4
Requires-Dist: llama-index-core<0.15,>=0.13.0
